yarn_apps_exporter.py
yarn_apps_exporter-0.0.5.dist-info/AUTHORS
yarn_apps_exporter-0.0.5.dist-info/METADATA
yarn_apps_exporter-0.0.5.dist-info/WHEEL
yarn_apps_exporter-0.0.5.dist-info/entry_points.txt
yarn_apps_exporter-0.0.5.dist-info/pbr.json
yarn_apps_exporter-0.0.5.dist-info/top_level.txt
yarn_apps_exporter-0.0.5.dist-info/RECORD
