Metadata-Version: 2.1
Name: yarn-apps-exporter
Version: 0.0.5
Summary: Write YARN apps metrics for node_exporter textfile
Home-page: https://github.com/ei-grad/yarn-apps-exporter
Author: Andrew Grigorev
Author-email: andrew@ei-grad.ru
License: MIT
Project-URL: Bug Tracker, https://github.com/ei-grad/yarn-apps-exporter/issues
Keywords: yarn,prometheus
Platform: UNKNOWN
Classifier: Intended Audience :: Developers
Classifier: Intended Audience :: Information Technology
Classifier: License :: OSI Approved :: MIT License
Classifier: Operating System :: OS Independent
